arcus/__init__.py
arcus/client/__init__.py
arcus/client/client.py
arcus/env/__init__.py
arcus/env/env.py
arcus/prompt/__init__.py
arcus/prompt/api_models/__init__.py
arcus/prompt/api_models/completion_models.py
arcus/prompt/api_models/query_models.py
arcus/prompt/chunking/__init__.py
arcus/prompt/chunking/chunker.py
arcus/prompt/chunking/sentence_chunker.py
arcus/prompt/chunking/split_chars.py
arcus/prompt/dataset/__init__.py
arcus/prompt/dataset/dataset.py
arcus/prompt/document/__init__.py
arcus/prompt/document/document.py
arcus/prompt/embedding/__init__.py
arcus/prompt/embedding/embedding.py
arcus/prompt/embedding/embedding_vector.py
arcus/prompt/embedding/openai_embedding.py
arcus/prompt/engine/__init__.py
arcus/prompt/engine/config.py
arcus/prompt/engine/engine.py
arcus/prompt/indexing/__init__.py
arcus/prompt/indexing/index.py
arcus/prompt/indexing/nearest_neighbor.py
arcus/prompt/llm/__init__.py
arcus/prompt/llm/anthropic.py
arcus/prompt/llm/cohere.py
arcus/prompt/llm/config.py
arcus/prompt/llm/llm.py
arcus/prompt/llm/openai.py
arcus/prompt/message/__init__.py
arcus/prompt/message/message.py
arcus/prompt/mode/__init__.py
arcus/prompt/mode/mode.py
arcus/prompt/model_provider/__init__.py
arcus/prompt/model_provider/anthropic.py
arcus/prompt/model_provider/cohere.py
arcus/prompt/model_provider/error.py
arcus/prompt/model_provider/model_type.py
arcus/prompt/model_provider/openai.py
arcus/prompt/node/__init__.py
arcus/prompt/node/node.py
arcus/prompt/prompt/__init__.py
arcus/prompt/prompt/prompt.py
arcus/prompt/prompt/prompt_constructor.py
arcus/prompt/prompt/stuff_prompt_constructor.py
arcus/prompt/query/__init__.py
arcus/prompt/query/query.py
arcus/prompt/retriever/__init__.py
arcus/prompt/retriever/retriever.py
arcus/prompt/system/__init__.py
arcus/prompt/system/config.py
arcus/prompt/system/system.py
arcus/prompt/tokenizer/__init__.py
arcus/prompt/tokenizer/anthropic_tokenizer.py
arcus/prompt/tokenizer/cohere_tokenizer.py
arcusapi-0.2.2.dist-info/LICENSE
arcusapi-0.2.2.dist-info/METADATA
arcusapi-0.2.2.dist-info/WHEEL
arcusapi-0.2.2.dist-info/top_level.txt
arcusapi-0.2.2.dist-info/RECORD
