Metadata-Version: 2.1
Name: arcusapi
Version: 0.2.2
Summary: Arcus Data Platform Client SDK.
Author-email: "Arcus Inc." <sdk@arcus.co>
Project-URL: Homepage, https://www.arcus.co
Project-URL: Documentation, https://app.arcus.co/docs
Classifier: Development Status :: 3 - Alpha
Classifier: Programming Language :: Python :: 3
Classifier: License :: OSI Approved :: Apache Software License
Classifier: Operating System :: OS Independent
Requires-Python: <4.0,>=3.8
License-File: LICENSE
Requires-Dist: requests >=2.28.0
Requires-Dist: tiktoken >=0.5.1
Requires-Dist: openai >=1.2.2
Requires-Dist: psycopg >=3.1.13
Requires-Dist: psycopg-binary >=3.1.13
Requires-Dist: pgvector >=0.2.4
Requires-Dist: cohere >=4.32
Requires-Dist: tokenizers >=0.13.3
Requires-Dist: anthropic >=0.5.0
Requires-Dist: transformers >=4.28.1
Requires-Dist: pydantic >=1.10.0
